mdformat_myst_pef/LICENSE
mdformat_myst_pef/__init__.py
mdformat_myst_pef/_directives.py
mdformat_myst_pef/plugin.py
mdformat_myst_pef/py.typed
mdformat_py_edu_fr-0.2.1.dist-info/METADATA
mdformat_py_edu_fr-0.2.1.dist-info/WHEEL
mdformat_py_edu_fr-0.2.1.dist-info/entry_points.txt
mdformat_py_edu_fr-0.2.1.dist-info/licenses/LICENSE.txt
mdformat_py_edu_fr/__init__.py
mdformat_py_edu_fr/__main__.py
mdformat_py_edu_fr/format_with_jupytext.py
mdformat_py_edu_fr/jupytext.toml
mdformat_py_edu_fr/util_ruff.py
mdformat_py_edu_fr-0.2.1.dist-info/RECORD
