Metadata-Version: 2.4
Name: mdformat-py-edu-fr
Version: 0.2.1
Summary: Tiny wrapper around mdformat for the py-edu-fr project
Author-Email: Pierre Augier <pierre.augier@univ-grenoble-alpes.fr>
License-Expression: BSD-3-Clause
License-File: LICENSE.txt
Requires-Python: >=3.13
Requires-Dist: jupytext
Requires-Dist: mdformat>=0.7.0
Requires-Dist: mdit-py-plugins>=0.3.0
Requires-Dist: mdformat-frontmatter>=0.3.2
Requires-Dist: mdformat-footnote>=0.1.1
Requires-Dist: mdformat-gfm>=1.0.0
Requires-Dist: ruamel.yaml>=0.16.0
Requires-Dist: ruff
